{
 "charts": [],
 "content": "[{\"id\":\"kMO3A_Pi9d\",\"type\":\"header\",\"data\":{\"text\":\"<span class=\\\"h4\\\">FDS App Bookings</span>\",\"col\":12}},{\"id\":\"TpXgrsz290\",\"type\":\"card\",\"data\":{\"card_name\":\"Order\",\"col\":4}},{\"id\":\"_iTn91jg_b\",\"type\":\"card\",\"data\":{\"card_name\":\"Service\",\"col\":4}},{\"id\":\"XwaaS7_7Ww\",\"type\":\"card\",\"data\":{\"card_name\":\"People\",\"col\":4}},{\"id\":\"QI0jf5iSMB\",\"type\":\"card\",\"data\":{\"card_name\":\"Location\",\"col\":4}},{\"id\":\"R_1scct5QB\",\"type\":\"card\",\"data\":{\"card_name\":\"Settings\",\"col\":4}}]",
 "creation": "2026-02-12 14:51:02.718655",
 "custom_blocks": [],
 "docstatus": 0,
 "doctype": "Workspace",
 "for_user": "",
 "hide_custom": 0,
 "icon": "small-file",
 "idx": 0,
 "indicator_color": "red",
 "is_hidden": 0,
 "label": "FDS App Bookings",
 "links": [
  {
   "hidden": 0,
   "is_query_report": 0,
   "label": "Order",
   "link_count": 2,
   "link_type": "DocType",
   "onboard": 0,
   "type": "Card Break"
  },
  {
   "hidden": 0,
   "is_query_report": 0,
   "label": "Orders",
   "link_count": 0,
   "link_to": "Order",
   "link_type": "DocType",
   "onboard": 0,
   "type": "Link"
  },
  {
   "hidden": 0,
   "is_query_report": 0,
   "label": "Invoices",
   "link_count": 0,
   "link_to": "Sales Invoice",
   "link_type": "DocType",
   "onboard": 0,
   "type": "Link"
  },
  {
   "hidden": 0,
   "is_query_report": 0,
   "label": "Service",
   "link_count": 4,
   "link_type": "DocType",
   "onboard": 0,
   "type": "Card Break"
  },
  {
   "hidden": 0,
   "is_query_report": 0,
   "label": "Categories",
   "link_count": 0,
   "link_to": "Item Group",
   "link_type": "DocType",
   "onboard": 0,
   "type": "Link"
  },
  {
   "hidden": 0,
   "is_query_report": 0,
   "label": "Services",
   "link_count": 0,
   "link_to": "Item",
   "link_type": "DocType",
   "onboard": 0,
   "type": "Link"
  },
  {
   "hidden": 0,
   "is_query_report": 0,
   "label": "Variations",
   "link_count": 0,
   "link_to": "Variations",
   "link_type": "DocType",
   "onboard": 0,
   "type": "Link"
  },
  {
   "hidden": 0,
   "is_query_report": 0,
   "label": "Units",
   "link_count": 0,
   "link_to": "Units",
   "link_type": "DocType",
   "onboard": 0,
   "type": "Link"
  },
  {
   "hidden": 0,
   "is_query_report": 0,
   "label": "People",
   "link_count": 4,
   "link_type": "DocType",
   "onboard": 0,
   "type": "Card Break"
  },
  {
   "hidden": 0,
   "is_query_report": 0,
   "label": "Users",
   "link_count": 0,
   "link_to": "User",
   "link_type": "DocType",
   "onboard": 0,
   "type": "Link"
  },
  {
   "hidden": 0,
   "is_query_report": 0,
   "label": "Customers",
   "link_count": 0,
   "link_to": "Customer",
   "link_type": "DocType",
   "onboard": 0,
   "type": "Link"
  },
  {
   "hidden": 0,
   "is_query_report": 0,
   "label": "Drivers",
   "link_count": 0,
   "link_to": "Drivers",
   "link_type": "DocType",
   "onboard": 0,
   "type": "Link"
  },
  {
   "hidden": 0,
   "is_query_report": 0,
   "label": "Reviews",
   "link_count": 0,
   "link_to": "Reviews",
   "link_type": "DocType",
   "onboard": 0,
   "type": "Link"
  },
  {
   "hidden": 0,
   "is_query_report": 0,
   "label": "Location",
   "link_count": 3,
   "link_type": "DocType",
   "onboard": 0,
   "type": "Card Break"
  },
  {
   "hidden": 0,
   "is_query_report": 0,
   "label": "Regions",
   "link_count": 0,
   "link_to": "Region",
   "link_type": "DocType",
   "onboard": 0,
   "type": "Link"
  },
  {
   "hidden": 0,
   "is_query_report": 0,
   "label": "States",
   "link_count": 0,
   "link_to": "State",
   "link_type": "DocType",
   "onboard": 0,
   "type": "Link"
  },
  {
   "hidden": 0,
   "is_query_report": 0,
   "label": "Addresses",
   "link_count": 0,
   "link_to": "Customer Address",
   "link_type": "DocType",
   "onboard": 0,
   "type": "Link"
  },
  {
   "hidden": 0,
   "is_query_report": 0,
   "label": "Settings",
   "link_count": 1,
   "link_type": "DocType",
   "onboard": 0,
   "type": "Card Break"
  },
  {
   "hidden": 0,
   "is_query_report": 0,
   "label": "Sliders",
   "link_count": 0,
   "link_to": "Sliders",
   "link_type": "DocType",
   "onboard": 0,
   "type": "Link"
  }
 ],
 "modified": "2026-02-16 16:37:55.686314",
 "modified_by": "Administrator",
 "module": "FDS App",
 "name": "FDS App Bookings",
 "number_cards": [],
 "owner": "Administrator",
 "parent_page": "",
 "public": 1,
 "quick_lists": [],
 "roles": [],
 "sequence_id": 2.0,
 "shortcuts": [],
 "title": "FDS App Bookings"
}